setup.py
tttDistributions/Binomialdistribution.py
tttDistributions/Gaussiandistribution.py
tttDistributions/Generaldistribution.py
tttDistributions/__init__.py
tttDistributions.egg-info/PKG-INFO
tttDistributions.egg-info/SOURCES.txt
tttDistributions.egg-info/dependency_links.txt
tttDistributions.egg-info/not-zip-safe
tttDistributions.egg-info/top_level.txt