Metadata-Version: 1.0
Name: tttDistributions
Version: 0.1
Summary: Gaussian and Binomial distributions
Home-page: UNKNOWN
Author: EmmaW
Author-email: emmayt@outlook.com
License: UNKNOWN
Platform: UNKNOWN
